OTAUpdateManager.py
micropython_OTAUpdateManager-1.0.0.dist-info/LICENSE
micropython_OTAUpdateManager-1.0.0.dist-info/METADATA
micropython_OTAUpdateManager-1.0.0.dist-info/WHEEL
micropython_OTAUpdateManager-1.0.0.dist-info/top_level.txt
micropython_OTAUpdateManager-1.0.0.dist-info/RECORD
