Metadata-Version: 2.1
Name: micropython-OTAUpdateManager
Version: 1.0.0
Summary: Implementation of OTA for remote monitoring and controlling of IoT devices
Home-page: UNKNOWN
Author: Raghul Raj G
Author-email: raghulrajatmega328@gmail.com
License: UNKNOWN
Project-URL: Source, https://github.com/raghulrajg/MicroPython-OTAUpdateManager
Keywords: OTA,OTAUpdateManager,Update,Microcontroller,Micropython
Platform: UNKNOWN
Classifier: Programming Language :: Python :: 3
Classifier: License :: OSI Approved :: GNU General Public License v3 (GPLv3)
Classifier: Intended Audience :: Developers
Classifier: Topic :: Software Development :: Libraries :: Python Modules
